examples/__init__.py
examples/go_and_back.py
examples/play_song1.py
examples/play_song2.py
pyroombaadapter/__init__.py
pyroombaadapter/pyroombaadapter.py
tests/__init__.py
pyroombaadapter-0.1.1.dist-info/LICENSE
pyroombaadapter-0.1.1.dist-info/METADATA
pyroombaadapter-0.1.1.dist-info/WHEEL
pyroombaadapter-0.1.1.dist-info/top_level.txt
pyroombaadapter-0.1.1.dist-info/RECORD
