Metadata-Version: 2.1
Name: pyroombaadapter
Version: 0.1.1
Summary: A Python library for Roomba Open Interface
Home-page: https://github.com/AtsushiSakai/PyRoombaAdapter
Author: Atsushi Sakai
Author-email: asakaig@gmail.com
Maintainer: Atsushi Sakai
Maintainer-email: asakaig@gmail.com
License: MIT
Keywords: python roomba
Platform: UNKNOWN
Classifier: Programming Language :: Python :: 3
Classifier: License :: OSI Approved :: MIT License
Requires-Python: >3.6.0
Requires-Dist: pyserial
